LockonToolkit/__init__.py
LockonToolkit/dateutils/__init__.py
LockonToolkit/dateutils/trade_days_calendar/a_stock_calendar.json
LockonToolkit/decorator_utils/__init__.py
LockonToolkit/decorator_utils/cache.py
LockonToolkit/emlutils/MailReader.py
LockonToolkit/emlutils/MailSender.py
LockonToolkit/emlutils/__init__.py
LockonToolkit/fileutils/__init__.py
LockonToolkit/infoutils/__init__.py
LockonToolkit/magic/__init__.py
LockonToolkit/magic/automation.py
LockonToolkit/pdutils/__init__.py
LockonToolkit/pdutils/df_filter_lang_parser.py
LockonToolkit/spyder/MetaSpyder.py
LockonToolkit/spyder/__init__.py
LockonToolkit/spyder/asynic_spyder.py
LockonToolkit/typeutils/__init__.py
lockon_toolkit-1.1.2.dist-info/LICENSE
lockon_toolkit-1.1.2.dist-info/METADATA
lockon_toolkit-1.1.2.dist-info/WHEEL
lockon_toolkit-1.1.2.dist-info/top_level.txt
lockon_toolkit-1.1.2.dist-info/RECORD
