Metadata-Version: 2.1
Name: lockon_toolkit
Version: 1.1.2
Summary: I'm a rookie. Lockon Selfusing toolkit
Author-email: LockonZ <lockon_zhang@foxmail.com>
Maintainer-email: LockonZ <lockon_zhang@foxmail.com>
Project-URL: documentation, https://dev.lockon-zhang.xyz/docs/LockonTool/docs
Project-URL: Changelog, https://dev.lockon-zhang.xyz/docs/LockonTool/change_log
Classifier: Development Status :: 4 - Beta
Classifier: Programming Language :: Python :: 3
Classifier: License :: OSI Approved :: MIT License
Classifier: Operating System :: OS Independent
Requires-Python: >=3.7
License-File: LICENSE
Requires-Dist: pandas>=1.3.0
Requires-Dist: numpy>=1.20.0
Requires-Dist: aiohttp>=3.10.6
